LICENSE
README.md
setup.py
adopt_pytorch/__init__.py
adopt_pytorch/config.py
adopt_pytorch/data.py
adopt_pytorch/feature_ranking.py
adopt_pytorch/models.py
adopt_pytorch/visualization.py
adopt_pytorch.egg-info/PKG-INFO
adopt_pytorch.egg-info/SOURCES.txt
adopt_pytorch.egg-info/dependency_links.txt
adopt_pytorch.egg-info/requires.txt
adopt_pytorch.egg-info/top_level.txt
adopt_pytorch.egg-info/zip-safe